ftracer/__init__.py
ftracer-1.6.dist-info/LICENSE
ftracer-1.6.dist-info/METADATA
ftracer-1.6.dist-info/WHEEL
ftracer-1.6.dist-info/top_level.txt
ftracer-1.6.dist-info/RECORD
