Metadata-Version: 2.1
Name: ftracer
Version: 1.6
Summary: Decorator functions to trace invocation of functions and class methods.
Home-page: https://github.com/h-ohsaki/ftracer
Author: Hiroyuki Ohsaki
Author-email: ohsaki@lsnl.jp
Classifier: Programming Language :: Python :: 3
Classifier: License :: OSI Approved :: GNU General Public License v3 (GPLv3)
Classifier: Operating System :: OS Independent
License-File: LICENSE
Requires-Dist: ansiterm
